<?xml version="1.0" encoding="utf-8"?>
<odoo noupdate="1">

    <record id="kw_gem_generic_process_gem_sale_order_type1"
            model="generic.process.flow">
        <field name="name">GeoEvoMed Cases</field>
        <field name="code">geo-evo-med-sale-order</field>
        <field name="process_model_id"
               ref="kw_gem_generic_process.kw_gem_generic_process_sale_order"/>
    </record>

    <record id="kw_gem_generic_process_gem_slide_type1"
            model="generic.process.flow">
        <field name="name">GeoEvoMed Slide</field>
        <field name="code">geo-evo-med-slider</field>
        <field name="process_model_id"
               ref="kw_gem_generic_process.kw_gem_generic_process_kw_gem_slide"/>
    </record>

    <record id="kw_gem_generic_process_gem_cassette_type1"
            model="generic.process.flow">
        <field name="name">GeoEvoMed Cassette</field>
        <field name="code">geo-evo-med-cassette</field>
        <field name="process_model_id"
               ref="kw_gem_generic_process.kw_gem_generic_process_kw_gem_cassette"/>
    </record>

    <record id="kw_gem_generic_process_gem_sample_type1"
            model="generic.process.flow">
        <field name="name">GeoEvoMed Sample</field>
        <field name="code">geo-evo-med-sample</field>
        <field name="process_model_id"
               ref="kw_gem_generic_process.kw_gem_generic_process_kw_gem_sample"/>
    </record>

</odoo>
